{
  "topic": "你的人生剧本是哪本古书？",
  "topicNoPunc": "你的人生剧本是哪本古书",
  "goal": "看清你的性格、爱情、财富、事业、朋友和晚年剧本",
  "selectionRule": "完整测试共 32 道题，图里先放前 5 道。",
  "captionTitle": "你的人生剧本是哪本古书？",
  "title": "你的人生剧本是哪本古书？",
  "coverLines": [
    "你的人生剧本",
    "是哪",
    "一本书？"
  ],
  "options": [
    "我的人生必须有值得写下来的转折和人物弧光",
    "我更相信规律、复盘和长期避坑",
    "我在机会和竞争里才会真正进入状态",
    "我很在意风格、审美和不被生活磨平",
    "我对关系和情绪变化非常敏感",
    "我不适合普通剧本，更像来自另一个世界"
  ],
  "questions": [
    {
      "id": 1,
      "text": "如果把你的人生写成一本书，开篇最像：",
      "options": [
        {
          "key": "A",
          "text": "一个人带着强烈命运感登场，注定要留下名字"
        },
        {
          "key": "B",
          "text": "局势复杂，先看清成败规律再决定怎么走"
        },
        {
          "key": "C",
          "text": "多方势力登场，机会、联盟和竞争同时出现"
        },
        {
          "key": "D",
          "text": "几个有趣的人物出场，气质和风骨先立住"
        },
        {
          "key": "E",
          "text": "繁华里藏着敏感心事，关系和情绪慢慢铺开"
        },
        {
          "key": "F",
          "text": "世界很奇异，主角天赋特殊，没人能按常理解释"
        }
      ]
    },
    {
      "id": 2,
      "text": "别人最容易从你身上读到哪种底色？",
      "options": [
        {
          "key": "A",
          "text": "真实、有分量，像经历过大起大落的人"
        },
        {
          "key": "B",
          "text": "清醒、谨慎，像很早就懂得现实规律的人"
        },
        {
          "key": "C",
          "text": "有斗志、有策略，像随时准备进入一场局"
        },
        {
          "key": "D",
          "text": "有品味、有个性，不太愿意活得庸俗"
        },
        {
          "key": "E",
          "text": "细腻、敏感，能读懂关系里没说出口的东西"
        },
        {
          "key": "F",
          "text": "独特、跳脱，像不属于普通分类的人"
        }
      ]
    },
    {
      "id": 3,
      "text": "你最不想被写成哪种人？",
      "options": [
        {
          "key": "A",
          "text": "一生平淡，没有任何值得记下来的转折"
        },
        {
          "key": "B",
          "text": "看不懂局势，反复踩同一种坑"
        },
        {
          "key": "C",
          "text": "没有胜负心，也没有进入牌桌的资格"
        },
        {
          "key": "D",
          "text": "没有风格，只会跟着别人过标准人生"
        },
        {
          "key": "E",
          "text": "感情粗糙，不懂人心，也不懂自己的心"
        },
        {
          "key": "F",
          "text": "被迫正常，天赋和怪异都被磨平"
        }
      ]
    },
    {
      "id": 4,
      "text": "你的故事最需要哪种叙事视角？",
      "options": [
        {
          "key": "A",
          "text": "人物传记：看一个人如何被命运推到台前"
        },
        {
          "key": "B",
          "text": "历史镜头：看选择背后的规律和代价"
        },
        {
          "key": "C",
          "text": "群雄叙事：看资源、竞争和机会如何变化"
        },
        {
          "key": "D",
          "text": "人物清谈：看气质、审美和一句话里的锋芒"
        },
        {
          "key": "E",
          "text": "家族长卷：看关系、情感和命运如何牵动彼此"
        },
        {
          "key": "F",
          "text": "异闻图志：看那些无法被常规解释的天赋和欲望"
        }
      ]
    },
    {
      "id": 5,
      "text": "你做选择时最像哪种人？",
      "options": [
        {
          "key": "A",
          "text": "会问这件事值不值得我拿人生去赌一次"
        },
        {
          "key": "B",
          "text": "会先看前人怎么输、怎么赢，再下判断"
        },
        {
          "key": "C",
          "text": "会判断谁是盟友、谁是对手、机会在哪里"
        },
        {
          "key": "D",
          "text": "会看这件事是否符合我的风格和尊严"
        },
        {
          "key": "E",
          "text": "会先感受这件事会不会伤害关系和内心秩序"
        },
        {
          "key": "F",
          "text": "会问它能不能打开一个我没见过的新世界"
        }
      ]
    }
  ],
  "optionCount": 6,
  "pickCount": 3,
  "tags": [
    "性格测试",
    "趣味测试",
    "心理测试",
    "人生剧本",
    "人格测试",
    "红楼梦",
    "山海经",
    "小红书测试"
  ],
  "coverScene": {
    "type": "cardDecision",
    "leftLabel": "经典书籍",
    "rightLabel": "人生六维",
    "topLeft": "人生剧本测试",
    "topRight": "看第一反应",
    "footer": "先做 5 道题，看你的人生剧本是哪本书",
    "leftItems": [
      "史记",
      "红楼梦",
      "山海经"
    ],
    "rightItems": [
      "性格",
      "爱情",
      "财富"
    ],
    "leftTitle": "剧本匹配",
    "rightTitle": "结果报告",
    "stampText": "测"
  },
  "link": "https://mini-test.github.io/xhs-test-h5/test-life-book-script/"
}
